{
  "slug": "2021-country-mansion",
  "images": [
    {
      "path": "moreton01.jpg"
    },
    {
      "path": "moreton02.jpg"
    },
    {
      "path": "moreton03.jpg"
    },
    {
      "path": "moreton04.jpg"
    },
    {
      "path": "moreton06.jpg"
    },
    {
      "path": "moreton07.jpg"
    },
    {
      "path": "moreton08.jpg"
    },
    {
      "path": "moreton09.jpg"
    },
    {
      "path": "moreton10.jpg"
    },
    {
      "path": "moreton11.jpg"
    },
    {
      "path": "moreton12.jpg"
    },
    {
      "path": "moreton13.jpg"
    },
    {
      "path": "moreton14.jpg"
    },
    {
      "path": "moreton15.jpg"
    }
  ]
}
